aukit/__init__.py
aukit/audio_changer.py
aukit/audio_cli.py
aukit/audio_editor.py
aukit/audio_griffinlim.py
aukit/audio_io.py
aukit/audio_noise_remover.py
aukit/audio_normalizer.py
aukit/audio_player.py
aukit/audio_spectrogram.py
aukit/audio_tuner.py
aukit/audio_world.py
aukit-1.4.6.dist-info/METADATA
aukit-1.4.6.dist-info/WHEEL
aukit-1.4.6.dist-info/entry_points.txt
aukit-1.4.6.dist-info/top_level.txt
aukit-1.4.6.dist-info/RECORD
