Metadata-Version: 2.1
Name: aukit
Version: 1.4.6
Summary: audio toolkit
Home-page: https://github.com/KuangDD/aukit
Author: kuangdd
Author-email: kuangdd@foxmail.com
License: UNKNOWN
Platform: UNKNOWN
Classifier: Intended Audience :: Developers
Classifier: Topic :: Software Development :: Build Tools
Classifier: License :: OSI Approved :: MIT License
Classifier: Programming Language :: Python :: 3.5
Classifier: Programming Language :: Python :: 3.6
Classifier: Programming Language :: Python :: 3.7
Classifier: Operating System :: OS Independent
Requires-Python: >=3.5
Requires-Dist: librosa
Requires-Dist: pydub
Requires-Dist: scipy
Requires-Dist: numpy
Requires-Dist: dotmap
